webhook_sender
