Metadata-Version: 1.1
Name: webhook-sender
Version: 0.1.0.1
Summary: A helper for sending webhooks, with automatic retry and CLI.
Home-page: https://github.com/gitguild/webhook_sender
Author: Ira Miller
Author-email: ira@gitguild.com
License: MIT
Platform: UNKNOWN
Classifier: License :: OSI Approved :: MIT License
Classifier: Programming Language :: Python :: 2
Classifier: Topic :: Software Development :: Libraries
